xycrypto/__init__.py
xycrypto/hashes.py
xycrypto/hmac.py
xycrypto/padding.py
xycrypto/ciphers/__init__.py
xycrypto/ciphers/base.py
xycrypto/ciphers/utils.py
xycrypto/ciphers/Cryptography/__init__.py
xycrypto/ciphers/Cryptography/_base.py
xycrypto/ciphers/Cryptography/_core_block.py
xycrypto/ciphers/Cryptography/_core_stream.py
xycrypto/ciphers/Cryptography/_lib.py
xycrypto-0.9.dist-info/LICENSE
xycrypto-0.9.dist-info/METADATA
xycrypto-0.9.dist-info/WHEEL
xycrypto-0.9.dist-info/top_level.txt
xycrypto-0.9.dist-info/RECORD
