Metadata-Version: 2.1
Name: xycrypto
Version: 0.9
Summary: A friendly cryptographic primitives library.
Home-page: https://github.com/xymy/xycrypto
Author: xymy
Author-email: thyfan@163.com
License: MIT
Platform: UNKNOWN
Classifier: License :: OSI Approved
Classifier: License :: OSI Approved :: MIT License
Classifier: Operating System :: OS Independent
Classifier: Programming Language :: Python
Classifier: Programming Language :: Python :: 3
Classifier: Programming Language :: Python :: 3.6
Classifier: Programming Language :: Python :: 3.7
Classifier: Programming Language :: Python :: 3.8
Classifier: Topic :: Security
Classifier: Topic :: Security :: Cryptography
Requires-Python: >=3.6
Requires-Dist: cryptography (>=2.8)
